planets/__init__.py
planets/_planets.py
planets/cli.py
planets/pck_parser.py
planets-0.9.1.dist-info/METADATA
planets-0.9.1.dist-info/WHEEL
planets-0.9.1.dist-info/entry_points.txt
planets-0.9.1.dist-info/licenses/AUTHORS.md
planets-0.9.1.dist-info/licenses/LICENSE
planets-0.9.1.dist-info/RECORD
