Metadata-Version: 2.4
Name: planets
Version: 0.9.1
Summary: Library to provide planetary constants
Project-URL: Homepage, https://github.com/michaelaye/planets
Project-URL: Documentation, https://planets.readthedocs.io
Project-URL: Bug Tracker, https://github.com/michaelaye/planets/issues
Project-URL: Changelog, https://github.com/michaelaye/planets/blob/main/CHANGELOG.md
Author-email: "K.-Michael Aye" <kmichael.aye@gmail.com>
License: MIT
License-File: AUTHORS.md
License-File: LICENSE
Keywords: astronomy,constants,planetary-science,planets
Classifier: Development Status :: 2 - Pre-Alpha
Classifier: Intended Audience :: Developers
Classifier: License :: OSI Approved :: MIT License
Classifier: Natural Language :: English
Classifier: Programming Language :: Python :: 3
Classifier: Programming Language :: Python :: 3.7
Classifier: Programming Language :: Python :: 3.8
Classifier: Programming Language :: Python :: 3.9
Classifier: Programming Language :: Python :: 3.10
Classifier: Programming Language :: Python :: 3.11
Classifier: Programming Language :: Python :: 3.12
Requires-Python: >=3.7
Requires-Dist: astropy
Requires-Dist: pooch
Provides-Extra: dev
Requires-Dist: pytest; extra == 'dev'
Requires-Dist: pytest-cov; extra == 'dev'
Requires-Dist: recommonmark; extra == 'dev'
Requires-Dist: ruff; extra == 'dev'
Requires-Dist: sphinx; extra == 'dev'
Requires-Dist: sphinx-markdown-tables; extra == 'dev'
